{
  "source": "Cal eProcure",
  "external_id": "0000039185",
  "title": "IFB A251017444 OneStream Implementation Services",
  "dept": "Office of Emergency Services",
  "description": "Event Details\nEvent : 0000039185\nIFB A251017444 OneStream Implementation Services\nDetails\n\nEvent ID\n0000039185\n\nFormat/Type:\nSell Event / RFx\n\nPublished Date\n05/06/2026  4:25PM PDT\n\nDept:\nOffice of Emergency Services\n\nEvent Version\n1\n\nEvent End Date:\n06/10/2026  5:00PM PDT\n\nDescription:\n\n\nThe California Governor¿s Office of Emergency Services, requires implementation and configuration services for the Software as a Service (SaaS) platform, OneStream. The system will support budget development, financial tracking, reporting, position control, grant management, and compliance oversight. The solution will replace manual processes, reduce reliance on spreadsheets, and provide a controlled, auditable financial management environment.\nView Event Package\nView Vendor Ads\nContact Information\nFlora Karami\nPhone: 916/845-8808\n\nEmail: flora.karami@caloes.ca.gov\nPre Bid Conference(N/A)\nMandatory: Non Mandatory\nDate:  \nTime:  \nLocation:  \nComments:  \n\nUNSPSC Codes\nUNSPSC Classification\tUNSPSC Classification Description\n81162000\tInformation Technology Service Delivery - Cloud-based software as a srvc\n81162004\tInformation Technology Service Delivery - Cloud-based software as a srvc - Database management as a srvcs\n81162005\tInformation Technology Service Delivery - Cloud-based software as a srvc - Dispatch software as a srvcs\n81162100\tInformation Technology Service Delivery - Cloud-based platform as a srvc\n81162103\tInformation Technology Service Delivery - Cloud-based platform as a srvc - Platform software as a srvcs\n81162204\tInformation Technology Service Delivery - Cloud-based infrastructure as a srvc - Cloud network devices as a srvcs\n81162303\tInformation Technology Service Delivery - Cloud-based business process as a srvcs - Content management process as a srvcs\nContractor License Type \n(N/A)\nService Area \n(N/A)",
  "published_date": "2026-05-06T16:25:00-07:00",
  "due_date": "2026-06-10T17:00:00-07:00",
  "contact_name": "Flora Karami",
  "contact_email": "flora.karami@caloes.ca.gov",
  "contact_phone": "916/845-8808",
  "status": "active",
  "is_relevant": true,
  "content_hash": "v1-0000039185-cc6dda31a50f",
  "metadata": {
    "event_type": "Sell Event / RFx",
    "event_version": 1,
    "mandatory_bidder_conference": {
      "required": false
    },
    "documents": [
      {
        "label": "IFB_A251017444_OneStream_Implementation.pdf",
        "url": "https://drive.google.com/file/d/1MiEAVF6SmY5c5gUiS9RK-vIMRVWbeYmp/view?usp=drivesdk",
        "type": "primary_spec",
        "attachment_description": ""
      }
    ],
    "unspsc_codes": [
      {
        "code": "01012001",
        "description": "/> <span data-if-container-label=\"conferenceRow\" data-if-source=\"[id^='ZZ_BID_CNF_VW_DUE_DT_TIME$']\" data-if-content=\"nu"
      }
    ]
  }
}
